README.md
setup.py
ark_nlp/__init__.py
ark_nlp.egg-info/PKG-INFO
ark_nlp.egg-info/SOURCES.txt
ark_nlp.egg-info/dependency_links.txt
ark_nlp.egg-info/not-zip-safe
ark_nlp.egg-info/requires.txt
ark_nlp.egg-info/top_level.txt
ark_nlp/dataset/__init__.py
ark_nlp/dataset/biaffine_named_entity_recognition_dataset.py
ark_nlp/dataset/bio_named_entity_recognition_dataset.py
ark_nlp/dataset/global_pointer_named_entity_recognition_dataset.py
ark_nlp/dataset/span_named_entity_recognition_dataset.py
ark_nlp/dataset/text_classification_dataset.py
ark_nlp/dataset/text_level_gcn_dataset.py
ark_nlp/dataset/text_match_dataset.py
ark_nlp/dataset/base/__init__.py
ark_nlp/dataset/base/_dataset.py
ark_nlp/dataset/base/_sentence_classification_dataset.py
ark_nlp/dataset/base/_token_classification_dataset.py
ark_nlp/factory/__init__.py
ark_nlp/factory/loss_function/__init__.py
ark_nlp/factory/loss_function/casrel_loss.py
ark_nlp/factory/loss_function/focal_loss.py
ark_nlp/factory/loss_function/global_pointer_ce_loss.py
ark_nlp/factory/loss_function/label_smoothing_ce_loss.py
ark_nlp/factory/loss_function/r_drop_cross_entropy_loss.py
ark_nlp/factory/lr_scheduler/__init__.py
ark_nlp/factory/metric/__init__.py
ark_nlp/factory/predictor/__init__.py
ark_nlp/factory/predictor/biaffine_named_entity_recognition.py
ark_nlp/factory/predictor/bio_named_entity_recognition.py
ark_nlp/factory/predictor/crf_named_entity_recognition.py
ark_nlp/factory/predictor/global_pointer_named_entity_recognition.py
ark_nlp/factory/predictor/span_named_entity_recognition.py
ark_nlp/factory/predictor/text_classification.py
ark_nlp/factory/predictor/text_match.py
ark_nlp/factory/predictor/base/__init__.py
ark_nlp/factory/predictor/base/_predictor.py
ark_nlp/factory/predictor/base/_sequence_classification.py
ark_nlp/factory/predictor/base/_token_classification.py
ark_nlp/factory/task/__init__.py
ark_nlp/factory/task/named_entity_recognition.py
ark_nlp/factory/task/text_classification.py
ark_nlp/factory/task/text_level_gcn_classification.py
ark_nlp/factory/task/text_match.py
ark_nlp/nn/__init__.py
ark_nlp/nn/biaffine_bert.py
ark_nlp/nn/crf_bert.py
ark_nlp/nn/global_pointer_bert.py
