Metadata-Version: 1.1
Name: ark-nlp
Version: 0.0.4
Summary: A private nlp coding package
Home-page: UNKNOWN
Author: Xiang Wang
Author-email: xiangking1995@163.com
License: MIT
Platform: UNKNOWN
Classifier: Intended Audience :: Developers
Classifier: Topic :: Software Development :: Libraries
Classifier: License :: OSI Approved :: MIT License
Classifier: Programming Language :: Python
